testing/membership_and_termination.py
testing/minflux.py
testing/polygons_2d.py
testing/test_voidwalker.py
testing/toy_2d.py
voidwalker/__init__.py
voidwalker/void.py
voidwalking-0.1.0.dist-info/licenses/LICENCE
voidwalking-0.1.0.dist-info/METADATA
voidwalking-0.1.0.dist-info/WHEEL
voidwalking-0.1.0.dist-info/top_level.txt
voidwalking-0.1.0.dist-info/RECORD
