Metadata-Version: 2.4
Name: voidwalking
Version: 0.1.0
Summary: Empty space finder for point pattern data. Point repulsive voids with various seeding options undergo growth and random walks to find maximally empty space in data
Author-email: Jack Peyton <jpeyton01@qub.ac.uk>
License: MIT License
Requires-Python: >=3.8
License-File: LICENCE
Dynamic: license-file
